<?xml version="1.0" encoding="UTF-8" ?>
<!DOCTYPE tiles-definitions PUBLIC
       "-//Apache Software Foundation//DTD Tiles Configuration 2.0//EN"
       "http://tiles.apache.org/dtds/tiles-config_2_0.dtd">

<tiles-definitions>
<!--base layout  -->
	<definition name="rhip.ehr.layout" template="/WEB-INF/views/manage/layouts/baseLayout.jsp">
        <put-attribute name="title" value="Founder" />
        <put-attribute name="header" value="/WEB-INF/views/manage/layouts/header.jsp" />
        <put-attribute name="loginbar" value="/WEB-INF/views/manage/layouts/loginbar.jsp" />
        <put-attribute name="left" value="/WEB-INF/views/manage/layouts/left.jsp" />
        <put-attribute name="content" value="/" />
    </definition>
    
    <definition name="rhip.portal.manage.login" template="/WEB-INF/views/manage/login/login.jsp"></definition>
    
    <definition name="rhip.portal.manage.home" extends="rhip.ehr.layout">
    	<put-attribute name="content" value="/WEB-INF/views/manage/layouts/homepage.jsp" />
    </definition>
    


     <!-- 服务信息类别 -->
    <definition name="rhip.portal.serviceInfo.edit" template="/WEB-INF/views/manage/serviceInfo/edit.jsp"></definition>
    <definition name="rhip.portal.infoType.index" template="/WEB-INF/views/manage/infoType/main_search.jsp"></definition>
    <definition name="rhip.portal.infoType.records" template="/WEB-INF/views/manage/infoType/infoType_records.jsp"></definition>
    <definition name="rhip.portal.infoType.addRecord" template="/WEB-INF/views/manage/infoType/addOrModify_record.jsp"></definition>
    <definition name="rhip.portal.infoType.modifyRecord" template="/WEB-INF/views/manage/infoType/addOrModify_record.jsp"></definition>
    <definition name="rhip.portal.infoType.subRecords" template="/WEB-INF/views/manage/infoType/subInfoTypeRecords.jsp"></definition>
    

    <definition name="rhip.portal.serviceInfo.search" template="/WEB-INF/views/manage/serviceInfo/search.jsp"></definition>
    <definition name="rhip.portal.serviceInfo.list" template="/WEB-INF/views/manage/serviceInfo/list.jsp"></definition>
    <definition name="rhip.portal.serviceInfo.type" template="/WEB-INF/views/manage/serviceInfo/type.jsp"></definition>
    
    <!-- 医院信息 -->
    <definition name="rhip.portal.hospitalInfo.search" template="/WEB-INF/views/manage/hospitalInfo/search.jsp"></definition>
    <definition name="rhip.portal.hospitalInfo.record" template="/WEB-INF/views/manage/hospitalInfo/record.jsp"></definition>
    <definition name="rhip.portal.hospitalInfo.list" template="/WEB-INF/views/manage/hospitalInfo/list.jsp"></definition>
    
    <definition name="rhip.ehr.msg" template="/WEB-INF/views/common/msg.jsp"></definition>
    
    <!-- 账户管理 -->
    <definition name="rhip.portal.accountInfo.search" template="/WEB-INF/views/manage/accountInfo/search.jsp"></definition>
    <definition name="rhip.portal.accountInfo.list" template="/WEB-INF/views/manage/accountInfo/list.jsp"></definition>
    <definition name="rhip.portal.accountInfo.showAccountInfo" template="/WEB-INF/views/manage/accountInfo/accountInfoShowPage.jsp"></definition>
</tiles-definitions>
